dff.v
// active-low set and resets 
// D - Flip Flops
// Non - Blocking assignments 
module dff(q,qbar,d,set,reset,clk);
    input d,set,reset,clk;
    output reg q;
    output qbar;
    assign qbar = ~q;

    always @(posedge clk)
        begin
            if(!reset) q<=0;
            else if(!set) q<=1;
            else q<=d;
        end
    
endmodule

dff-test.v
module testbench;
    reg d,set,reset,clk;
    wire q,qbar;
    dff DUT(q,qbar,d,set,reset,clk);

    always #5 clk = ~ clk;
    initial begin
        $dumpfile("dff.vcd");
        $dumpvars(0,testbench);
        clk = 0; d = 0; set = 1; reset = 1;
        $monitor("Time=%0t | clk=%b reset=%b set=%b d=%b | q=%b qbar=%b",$time,clk,reset,set,d,q,qbar);

        #2 d = 1;
        #8;

        #2 d = 0;
        #8;

        #2 set = 1;

        #2 reset = 0;
        #8;

        #2 reset = 1;

        #2 set = 0; reset = 0;
        #8;

        #2 set = 1; reset = 1; d = 1;
        #8

        $finish;

    end
endmodule

dff.vcd
$date
	Sun Aug 30 01:04:02 2026
$end
$version
	Icarus Verilog
$end
$timescale
	1s
$end
$scope module testbench $end
$var wire 1 ! qbar $end
$var wire 1 " q $end
$var reg 1 # clk $end
$var reg 1 $ d $end
$var reg 1 % reset $end
$var reg 1 & set $end
$scope module DUT $end
$var wire 1 # clk $end
$var wire 1 $ d $end
$var wire 1 ! qbar $end
$var wire 1 % reset $end
$var wire 1 & set $end
$var reg 1 " q $end
$upscope $end
$upscope $end
$enddefinitions $end
$comment Show the parameter values. $end
$dumpall
$end
#0
$dumpvars
1&
1%
0$
0#
x"
x!
$end
#2
1$
#5
0!
1"
1#
#10
0#
#12
0$
#15
1!
0"
1#
#20
0#
#24
0%
#25
1#
#30
0#
#34
1%
#35
1#
#36
0%
0&
#40
0#
#45
1#
#46
1$
1%
1&
