prac.v
// this is my go to practice workspace file 
// in this I will be updating my practiced examples and this file might keep on changing frequently 
module mux21(in1,in0,s,f);
    input in1,in0,s;
    output reg f;
    always @(in1 or in0 or s)
    begin
        if(s)
            f = in1;
        else 
            f = in0; 
    end
endmodule

prac-test.v
module testbench;

    reg in1, in0, s;
    wire f;

    // Instantiate DUT
    mux21 M1(
        .in1(in1),
        .in0(in0),
        .s(s),
        .f(f)
    );

    initial begin
        $dumpfile("prac.vcd");
        $dumpvars(0,testbench);   
        // Display values whenever they change
        $monitor("Time=%0t | in1=%b in0=%b s=%b | f=%b",
                 $time, in1, in0, s, f);

        // Test 1
        in1 = 0;
        in0 = 0;
        s = 0;
        #10;

        // Test 2
        in1 = 0;
        in0 = 1;
        s = 0;
        #10;

        // Test 3
        in1 = 1;
        in0 = 0;
        s = 0;
        #10;

        // Test 4
        in1 = 1;
        in0 = 1;
        s = 0;
        #10;

        // Test 5
        in1 = 0;
        in0 = 0;
        s = 1;
        #10;

        // Test 6
        in1 = 0;
        in0 = 1;
        s = 1;
        #10;

        // Test 7
        in1 = 1;
        in0 = 0;
        s = 1;
        #10;

        // Test 8
        in1 = 1;
        in0 = 1;
        s = 1;
        #10;

        $finish;

    end

endmodule

prac.vcd
$date
	Sun Aug 30 01:21:22 2026
$end
$version
	Icarus Verilog
$end
$timescale
	1s
$end
$scope module testbench $end
$var wire 1 ! f $end
$var reg 1 " in0 $end
$var reg 1 # in1 $end
$var reg 1 $ s $end
$scope module M1 $end
$var wire 1 " in0 $end
$var wire 1 # in1 $end
$var wire 1 $ s $end
$var reg 1 ! f $end
$upscope $end
$upscope $end
$enddefinitions $end
$comment Show the parameter values. $end
$dumpall
$end
#0
$dumpvars
0$
0#
0"
0!
$end
#10
1!
1"
#20
0!
0"
1#
#30
1!
1"
#40
0!
1$
0"
0#
#50
1"
#60
1!
0"
1#
#70
1"
