ringcounter.v
module ringcounter(clk,init,count);
    input clk,init;
    output reg[7:0] count;
    always @(posedge clk)
        begin
            if(init)
                count = 8'b10000000;
            else 
                begin
                    count <= count << 1;
                    count[0] <= count[7];
                end
        end
endmodule

ringcounter-test.v
module ringcounter_tb;

    reg clk;
    reg init;
    wire [7:0] count;

    ringcounter DUT (
        .clk(clk),
        .init(init),
        .count(count)
    );

    always #5 clk = ~clk;

    initial
    begin
        $dumpfile("ringcounter.vcd");
        $dumpvars(0, ringcounter_tb);

        clk  = 0;
        init = 0;

        #10;
        init = 1;

        #10;
        init = 0;

        #100;

        $finish;
    end

    // Display output
    initial
    begin
        $monitor("Time = %0t | clk = %b | init = %b | count = %b",
                 $time, clk, init, count);
    end

endmodule

ringcounter.vcd
$date
	Wed Sep 02 11:18:47 2026
$end
$version
	Icarus Verilog
$end
$timescale
	1s
$end
$scope module ringcounter_tb $end
$var wire 8 ! count [7:0] $end
$var reg 1 " clk $end
$var reg 1 # init $end
$scope module DUT $end
$var wire 1 " clk $end
$var wire 1 # init $end
$var reg 8 $ count [7:0] $end
$upscope $end
$upscope $end
$enddefinitions $end
$comment Show the parameter values. $end
$dumpall
$end
#0
$dumpvars
bx $
0#
0"
bx !
$end
#5
bx !
bx $
1"
#10
0"
1#
#15
b10000000 !
b10000000 $
1"
#20
0"
0#
#25
b1 !
b1 $
1"
#30
0"
#35
b10 !
b10 $
1"
#40
0"
#45
b100 !
b100 $
1"
#50
0"
#55
b1000 !
b1000 $
1"
#60
0"
#65
b10000 !
b10000 $
1"
#70
0"
#75
b100000 !
b100000 $
1"
#80
0"
#85
b1000000 !
b1000000 $
1"
#90
0"
#95
b10000000 !
b10000000 $
1"
#100
0"
#105
b1 !
b1 $
1"
#110
0"
#115
b10 !
b10 $
1"
