up_down_counter.v
module up_down_counter(mode,clr,ld,d_in,clk,count);
    input mode,clr,clk,ld;
    parameter N = 7;
    input [0:N] d_in;
    output reg [0:N]count;
    always @(posedge clk) begin
        if(ld) count <= d_in;
        else if(clr) count <= 0;
        else if(mode) count <= count + 1;
        else count <= count - 1;
    end
endmodule

up_down_counter-test.v
module testbench;

    reg mode;
    reg clr;
    reg ld;
    reg clk;
    reg [7:0] d_in;
    wire [7:0] count;

    up_down_counter DUT (
        .mode(mode),
        .clr(clr),
        .ld(ld),
        .d_in(d_in),
        .clk(clk),
        .count(count)
    );

    always #5 clk = ~clk;

    initial begin
        $dumpfile("up_down_counter.vcd");
        $dumpvars(0, testbench);

        $monitor("Time=%0t | mode=%b clr=%b ld=%b d_in=%d | count=%d",
                 $time, mode, clr, ld, d_in, count);

        // Initial values
        clk  = 0;
        mode = 0;
        clr  = 0;
        ld   = 0;
        d_in = 8'd0;

        
        #2;
        d_in = 8'd10;
        ld = 1;
        #8;
        ld = 0;

        // Count UP
        mode = 1;
        #40;

        // Count DOWN
        mode = 0;
        #40;

        // Clear
        clr = 1;
        #10;
        clr = 0;

        // Load 250
        d_in = 8'd250;
        ld = 1;
        #10;
        ld = 0;

        // Count UP to demonstrate overflow
        mode = 1;
        #70;

        // Count DOWN
        mode = 0;
        #30;

        $finish;
    end

endmodule

up_down_counter.vcd
$date
	Wed Sep 02 10:35:55 2026
$end
$version
	Icarus Verilog
$end
$timescale
	1s
$end
$scope module testbench $end
$var wire 8 ! count [7:0] $end
$var reg 1 " clk $end
$var reg 1 # clr $end
$var reg 8 $ d_in [7:0] $end
$var reg 1 % ld $end
$var reg 1 & mode $end
$scope module DUT $end
$var wire 1 " clk $end
$var wire 1 # clr $end
$var wire 33 ' d_in [0:32] $end
$var wire 1 % ld $end
$var wire 1 & mode $end
$var parameter 32 ( N $end
$var reg 33 ) count [0:32] $end
$upscope $end
$upscope $end
$enddefinitions $end
$comment Show the parameter values. $end
$dumpall
b100000 (
$end
#0
$dumpvars
bx )
b0 '
0&
0%
b0 $
0#
0"
bx !
$end
#2
1%
b1010 '
b1010 $
#5
b1010 !
b1010 )
1"
#10
0"
1&
0%
#15
b1011 !
b1011 )
1"
#20
0"
#25
b1100 !
b1100 )
1"
#30
0"
#35
b1101 !
b1101 )
1"
#40
0"
#45
b1110 !
b1110 )
1"
#50
0"
0&
#55
b1101 !
b1101 )
1"
#60
0"
#65
b1100 !
b1100 )
1"
#70
0"
#75
b1011 !
b1011 )
1"
#80
0"
#85
b1010 !
b1010 )
1"
#90
0"
1#
#95
b0 !
b0 )
1"
#100
0"
1%
b11111010 '
b11111010 $
0#
#105
b11111010 !
b11111010 )
1"
#110
0"
1&
0%
#115
b11111011 !
b11111011 )
1"
#120
0"
#125
b11111100 !
b11111100 )
1"
#130
0"
#135
b11111101 !
b11111101 )
1"
#140
0"
#145
b11111110 !
b11111110 )
1"
#150
0"
#155
b11111111 !
b11111111 )
1"
#160
0"
#165
b0 !
b100000000 )
1"
#170
0"
#175
b1 !
b100000001 )
1"
#180
0"
0&
#185
b0 !
b100000000 )
1"
#190
0"
#195
b11111111 !
b11111111 )
1"
#200
0"
#205
b11111110 !
b11111110 )
1"
